aiopaperscroll/__init__.py
aiopaperscroll/client.py
aiopaperscroll/exceptions.py
aiopaperscroll/methods.py
aiopaperscroll-1.0.0.dist-info/LICENSE
aiopaperscroll-1.0.0.dist-info/METADATA
aiopaperscroll-1.0.0.dist-info/WHEEL
aiopaperscroll-1.0.0.dist-info/top_level.txt
aiopaperscroll-1.0.0.dist-info/RECORD
